__init__.py
acrcloud/__init__.py
acrcloud/client.py
acrcloudclient-0.0.4.dist-info/LICENSE.md
acrcloudclient-0.0.4.dist-info/METADATA
acrcloudclient-0.0.4.dist-info/WHEEL
acrcloudclient-0.0.4.dist-info/top_level.txt
acrcloudclient-0.0.4.dist-info/RECORD
