Metadata-Version: 2.1
Name: acrcloudclient
Version: 0.0.4
Summary: An AcrCloud Client for Python
Author-email: Gonzalo Martinez <gonzafirewall@gmail.com>
Project-URL: Homepage, https://github.com/gonzafirewall/acrcloud
Project-URL: Bug Tracker, https://github.com/gonzafirewall/acrcloud/issues
Classifier: Programming Language :: Python :: 3
Classifier: License :: OSI Approved :: MIT License
Classifier: Operating System :: OS Independent
Requires-Python: >=3.7
License-File: LICENSE.md
Requires-Dist: requests
